<?xml version="1.0"?><players><player><name>TEST</name><maxLevel>100</maxLevel><highScore>0, 0</highScore><highScore>1, 100</highScore><highScore>2, 500</highScore><highScore>3, 1000</highScore></player><player><name>CC</name><maxLevel>1</maxLevel></player><player><name>P1</name><maxLevel>1</maxLevel></player><player><name>SAM</name><maxLevel>3</maxLevel><highScore>1, 128</highScore></player><player><name>OLLIE</name><maxLevel>4</maxLevel><highScore>1, 83</highScore><highScore>2, 238</highScore><highScore>3, 267</highScore></player><player><name>SAMHITHA</name><maxLevel>1</maxLevel></player><player><name>TEST </name><maxLevel>1</maxLevel></player><player><name>ENTER YOUR NAME...</name><maxLevel>1</maxLevel></player></players>